{
    "sign": "racecar_track",
    "signer": "aslLex",
    "uid": "000",
    "synonyms": null,
    "handshapes": {
        "begin": {
            "d": "s",
            "nd": "s"
        },
        "end": {
            "d": "a",
            "nd": "a"
        }
    },
    "regions": {
        "morph1_general": "Neutral",
        "morph1_specific": "Neutral",
        "morph1_specific_second": "Neutral",
        "morph1_contact": 1.0,
        "morph1_signtype": "SymmetricalOrAlternating",
        "morph1_movement": "Straight",
        "morph1_repeat": 1,
        "morph2_general": "Neutral",
        "morph2_specific": "Neutral",
        "morph2_specific_second": null,
        "morph2_contact": 1.0,
        "morph2_signtype": "SymmetricalOrAlternating",
        "morph2_movement": "None",
        "morph2_repeat": 1.0
    },
    "hands": "SymmetricalOrAlternating",
    "num_positions": 2,
    "positions": [],
    "motion": {},
    "palmface": "",
    "wristTurn": [
        0,
        1.0
    ],
    "morphemes": 3,
    "complexity": null,
    "frequency": 4.083,
    "category": null
}