
{

"@a15067@em2@japanese-dolls": { 
	"vb": "75 75 -0 -0",
 },
"@a17299@fir@u1f38e-japanesedolls": { 
	"vb": "75 75 -0 -75",
 },
"@a28508@jqe@japanese-dolls": { 
	"vb": "75 71 -142 -148",
 },
"@a39763@noc@japanese-dolls": { 
	"vb": "75 75 -75 -0",
 },
"@a42248@nog@japanese-dolls-activities": { 
	"vb": "75 39 -0 -150",
 },
"@a44453@not@japanese-dolls": { 
	"vb": "75 73 -142 -75",
 },
"@a50559@tw2@japanese-dolls": { 
	"vb": "75 75 -150 -0",
 },
"@a51368@twe@japanese-dolls": { 
	"vb": "67 75 -75 -75",
 },
}
