
{

"@d78@mutcd@argentina_825": { 
	"vb": "75 75 -300 -0",
 },
"@d160@mutcd@australia_826": { 
	"vb": "75 75 -75 -75",
 },
"@d245@mutcd@brazil_827": { 
	"vb": "75 75 -150 -0",
 },
"@d330@mutcd@canada_828": { 
	"vb": "75 75 -75 -150",
 },
"@d407@mutcd@canada_ontario_829": { 
	"vb": "75 75 -75 -150",
 },
"@d495@mutcd@canada_quebec_830": { 
	"vb": "75 75 -150 -75",
 },
"@d578@mutcd@chile_831": { 
	"vb": "75 75 -225 -0",
 },
"@d661@mutcd@colombia_832": { 
	"vb": "75 75 -150 -150",
 },
"@d736@mutcd@ireland_834": { 
	"vb": "75 75 -225 -75",
 },
"@d821@mutcd@japan_835": { 
	"vb": "75 75 -225 -150",
 },
"@d865@mutcd@liberia_836": { 
	"vb": "75 75 -300 -75",
 },
"@d1019@mutcd@new_zealand_838": { 
	"vb": "75 75 -0 -0",
 },
"@d1100@mutcd@panama_839": { 
	"vb": "75 75 -0 -75",
 },
"@d1386@mutcd@united_states_840": { 
	"vb": "75 75 -75 -0",
 },
"@d1510@mutcd@uruguay_841": { 
	"vb": "75 75 -0 -150",
 },
}
