
{

"@a59391@ian@ascidian": { 
	"vb": "75 67 -75 -75",
 },
"@a59549@ian@bryozoan-colony": { 
	"vb": "61 75 -75 -142",
 },
"@a59920@ian@ctenophore": { 
	"vb": "71 75 -73 -0",
 },
"@a60050@ian@doliolid": { 
	"vb": "75 51 -136 -150",
 },
"@a60327@ian@fossil-trilobite": { 
	"vb": "73 75 -0 -0",
 },
"@a60729@ian@limulus-polyphemus": { 
	"vb": "43 75 -211 -150",
 },
"@a60886@ian@mnemiopsis-leidyi": { 
	"vb": "67 75 -150 -75",
 },
"@a60997@ian@neoesperiopsis-rigida": { 
	"vb": "41 75 -215 -0",
 },
"@a61570@ian@sea-squirt": { 
	"vb": "53 75 -0 -144",
 },
"@a61679@ian@sponge-1": { 
	"vb": "71 75 -144 -0",
 },
"@a61680@ian@sponge-2": { 
	"vb": "75 69 -0 -75",
 },
"@a61683@ian@springtail": { 
	"vb": "75 51 -136 -201",
 },
"@a61771@ian@tardigrade": { 
	"vb": "75 35 -53 -217",
 },
}
