
{

"@a58963@baianet@group": { 
	"vb": "75 75 -0 -0",
 },
"@a58968@baianet@group": { 
	"vb": "75 75 -75 -0",
 },
"@a58973@baianet@group": { 
	"vb": "75 75 -150 -0",
 },
"@a58978@baianet@group": { 
	"vb": "75 75 -0 -75",
 },
"@a58990@baianet@group": { 
	"vb": "75 67 -150 -600",
 },
"@a59003@baianet@group": { 
	"vb": "75 75 -75 -75",
 },
"@a59007@baianet@group": { 
	"vb": "75 75 -150 -75",
 },
"@a59012@baianet@group": { 
	"vb": "75 75 -0 -150",
 },
"@a59017@baianet@group": { 
	"vb": "75 75 -75 -150",
 },
"@a59022@baianet@group": { 
	"vb": "75 75 -150 -150",
 },
"@a59027@baianet@group": { 
	"vb": "75 75 -0 -225",
 },
"@a59032@baianet@group": { 
	"vb": "75 75 -75 -225",
 },
"@a59037@baianet@group": { 
	"vb": "75 75 -150 -225",
 },
"@a59042@baianet@group": { 
	"vb": "75 75 -0 -300",
 },
"@a59047@baianet@group": { 
	"vb": "75 75 -75 -300",
 },
"@a59059@baianet@group": { 
	"vb": "75 67 -150 -667",
 },
"@a59073@baianet@group": { 
	"vb": "75 75 -150 -300",
 },
"@a59078@baianet@group": { 
	"vb": "75 75 -0 -375",
 },
"@a59083@baianet@group": { 
	"vb": "75 75 -75 -375",
 },
"@a59088@baianet@group": { 
	"vb": "75 75 -150 -375",
 },
"@a59093@baianet@group": { 
	"vb": "75 75 -0 -450",
 },
"@a59097@baianet@group": { 
	"vb": "75 75 -75 -450",
 },
"@a59101@baianet@group": { 
	"vb": "75 75 -150 -450",
 },
"@a59105@baianet@group": { 
	"vb": "75 75 -0 -525",
 },
"@a59109@baianet@group": { 
	"vb": "75 75 -75 -525",
 },
"@a59113@baianet@group": { 
	"vb": "75 75 -150 -525",
 },
"@a59124@baianet@group": { 
	"vb": "75 67 -0 -675",
 },
"@a59138@baianet@group": { 
	"vb": "75 75 -0 -600",
 },
"@a59142@baianet@group": { 
	"vb": "75 75 -75 -600",
 },
"@a59177@baianet@group": { 
	"vb": "75 67 -75 -675",
 },
}
