
{

"@a863@awe@life-ring": { 
	"vb": "75 75 -300 -150",
 },
"@a1391@bat@support-2": { 
	"vb": "75 75 -0 -0",
 },
"@a1392@bat@support-3": { 
	"vb": "75 75 -0 -75",
 },
"@a1393@bat@support": { 
	"vb": "75 75 -0 -150",
 },
"@a3077@bri@support-2": { 
	"vb": "75 75 -150 -75",
 },
"@a26843@ibm@help-16": { 
	"vb": "75 75 -75 -0",
 },
"@a26844@ibm@help-b": { 
	"vb": "75 75 -75 -75",
 },
"@a26845@ibm@help-r": { 
	"vb": "75 75 -75 -150",
 },
"@a26846@ibm@help-t": { 
	"vb": "75 75 -150 -0",
 },
"@a31849@lug@support": { 
	"vb": "75 75 -150 -150",
 },
"@a36143@met@help": { 
	"vb": "75 75 -225 -0",
 },
"@a48336@roc@support": { 
	"vb": "69 75 -375 -148",
 },
"@a48531@sli@support": { 
	"vb": "75 75 -225 -75",
 },
"@a50125@the@support": { 
	"vb": "75 73 -375 -75",
 },
"@a52224@typ@support": { 
	"vb": "75 75 -225 -150",
 },
"@a54398@wav@life-ring": { 
	"vb": "75 75 -300 -0",
 },
"@a55993@web@support-1": { 
	"vb": "75 75 -375 -0",
 },
"@a55994@web@support": { 
	"vb": "75 75 -300 -75",
 },
}
