
{

"@a1810@bon@feelings-sad-6015-": { 
	"vb": "75 75 -0 -0",
 },
"@a1821@bon@felt-sad-5266": { 
	"vb": "75 47 -0 -75",
 },
"@a1822@bon@felt-sad-about-people-leaving-5267": { 
	"vb": "75 41 -0 -122",
 },
"@a38623@mul@sad-lady": { 
	"vb": "63 75 -75 -75",
 },
"@a48749@solver@1-sad-kid": { 
	"vb": "49 74 -144 -0",
 },
"@a49286@str@088-anxious-face": { 
	"vb": "69 75 -75 -0",
 },
"@d4245@wikim-ladyofhats@big_eyes": { 
	"vb": "59 75 -75 -150",
 },
"@d4285@wikim-ladyofhats@sad": { 
	"vb": "59 75 -134 -150",
 },
"@d4299@wikim-ladyofhats@whatface": { 
	"vb": "56 75 -138 -75",
 },
}
