
{

"@a60627@ian@kosteletzkya-virginica-1": { 
	"vb": "33 75 -362 -33",
 },
"@a60628@ian@kosteletzkya-virginica-2": { 
	"vb": "60 75 -132 -150",
 },
"@a61035@ian@odocoileus-virginianus-buck": { 
	"vb": "69 75 -0 -150",
 },
"@a61036@ian@odocoileus-virginianus-doe": { 
	"vb": "63 75 -69 -150",
 },
"@a61037@ian@odocoileus-virginianus-fawn": { 
	"vb": "49 75 -251 -149",
 },
"@a61953@ian@usa-chesapeake-bay-watershed": { 
	"vb": "61 75 -75 -0",
 },
"@a61958@ian@usa-de-md-va-coastal-bays-watershed-locator-map": { 
	"vb": "43 75 -300 -149",
 },
"@a61961@ian@usa-de-md-va-coastal-bays": { 
	"vb": "51 75 -195 -55",
 },
"@a61962@ian@usa-de-md-va-delmarva-line-map": { 
	"vb": "37 75 -343 -122",
 },
"@a61963@ian@usa-de-md-va-delmarva": { 
	"vb": "41 75 -321 -47",
 },
"@a62059@ian@usa-md-va-chesapeake-bay-3d-mountains-and-shelf": { 
	"vb": "75 43 -246 -106",
 },
"@a62060@ian@usa-md-va-chesapeake-bay-3d": { 
	"vb": "75 47 -270 -0",
 },
"@a62061@ian@usa-md-va-chesapeake-bay-line-map": { 
	"vb": "61 75 -75 -75",
 },
"@a62066@ian@usa-md-va-chincoteague-bay-3d-watershed": { 
	"vb": "75 55 -195 -0",
 },
"@a62070@ian@usa-md-va-chincoteague-sinepuxent": { 
	"vb": "59 75 -136 -0",
 },
"@a62124@ian@usa-va-james-river": { 
	"vb": "59 75 -136 -75",
 },
"@a62131@ian@usa-va-york-river-watershed-3d": { 
	"vb": "75 33 -345 -0",
 },
"@a62134@ian@usa-va-york-river-watershed": { 
	"vb": "75 51 -246 -55",
 },
"@a62135@ian@usa-va-york-river": { 
	"vb": "59 75 -192 -150",
 },
"@d3767@wikim-all@seal_of_virginia": { 
	"vb": "75 75 -0 -0",
 },
"@d3769@wikim-all@seal_of_west_virginia": { 
	"vb": "75 75 -0 -75",
 },
}
