
{

"@a15160@em2@money-with-wings": { 
	"vb": "75 75 -0 -0",
 },
"@a16488@emo@money-with-wings": { 
	"vb": "75 75 -0 -75",
 },
"@a17579@fir@u1f4b8-moneywithwings": { 
	"vb": "75 73 -75 -75",
 },
"@a28582@jqe@money-with-wings": { 
	"vb": "75 61 -150 -140",
 },
"@a39880@noc@money-w-wings": { 
	"vb": "75 55 -0 -150",
 },
"@a42697@nog@money-wings-objects": { 
	"vb": "75 65 -150 -75",
 },
"@a44520@not@money-with-wings": { 
	"vb": "75 55 -75 -148",
 },
"@a50662@tw2@money-with-wings": { 
	"vb": "75 75 -75 -0",
 },
"@a51432@twe@money-with-wings": { 
	"vb": "75 75 -150 -0",
 },
}
