
{

"@a613@awe@bar-chart": { 
	"vb": "75 59 -150 -292",
 },
"@a26645@ibm@bar-chart-16": { 
	"vb": "75 75 -0 -0",
 },
"@a26646@ibm@bar-chart-b": { 
	"vb": "75 65 -75 -225",
 },
"@a27392@icf@ecommerce-business-shopping-chart-bar": { 
	"vb": "75 67 -0 -225",
 },
"@a28966@jqu@bar-chart-o": { 
	"vb": "75 63 -75 -290",
 },
"@a30121@lib@chart-bar": { 
	"vb": "75 75 -75 -0",
 },
"@a32851@mat@chart-bar-stacked": { 
	"vb": "75 71 -150 -150",
 },
"@a32853@mat@chart-bar": { 
	"vb": "75 71 -150 -221",
 },
"@a36002@met@chart-bars": { 
	"vb": "75 63 -0 -292",
 },
"@a44102@not@bar-chart": { 
	"vb": "75 75 -150 -0",
 },
"@a51874@typ@chart-bar": { 
	"vb": "67 75 -0 -355",
 },
"@a53026@vaa@bar-chart-h": { 
	"vb": "75 75 -0 -75",
 },
"@a53027@vaa@bar-chart-v": { 
	"vb": "75 75 -75 -75",
 },
"@a53028@vaa@bar-chart": { 
	"vb": "73 75 -150 -351",
 },
"@a57551@xei@chart-bar-square": { 
	"vb": "75 75 -150 -75",
 },
"@a57552@xei@chart-bar": { 
	"vb": "73 75 -75 -353",
 },
"@b8125@web@bar-chart-1": { 
	"vb": "75 75 -0 -150",
 },
"@b8126@web@barchart": { 
	"vb": "75 75 -75 -150",
 },
}
