
{

"@a14793@em2@cookie": { 
	"vb": "75 75 -75 -0",
 },
"@a15864@emo@cookie": { 
	"vb": "75 75 -150 -0",
 },
"@a17265@fir@u1f36a-cookie": { 
	"vb": "75 75 -0 -73",
 },
"@a28297@jqe@cookie": { 
	"vb": "75 73 -0 -0",
 },
"@a33135@mat@cookie": { 
	"vb": "75 75 -75 -75",
 },
"@a39494@noc@cookie": { 
	"vb": "75 75 -150 -75",
 },
"@a41206@nog@cookie-food-drink": { 
	"vb": "75 75 -0 -148",
 },
"@a41810@nog@fortune-cookie-food-drink": { 
	"vb": "75 75 -75 -150",
 },
"@a44241@not@cookie": { 
	"vb": "75 75 -150 -150",
 },
"@a47827@plateau@cookie-cookies": { 
	"vb": "75 75 -0 -223",
 },
"@a49613@str@556-cookie": { 
	"vb": "73 75 -75 -225",
 },
"@a50334@tw2@cookie": { 
	"vb": "75 75 -148 -225",
 },
"@a50458@tw2@fortune-cookie": { 
	"vb": "73 75 -0 -298",
 },
"@a57603@xei@cookie": { 
	"vb": "75 75 -73 -300",
 },
"@b12430@gameicons-delapouite@cookie": { 
	"vb": "75 75 -148 -300",
 },
}
