{
    "sign": "attention-wave",
    "signer": "asl2english",
    "uid": 79,
    "synonyms": [],
    "handshapes": {
        "begin": {
            "d": 18,
            "nd": 18
        },
        "end": {
            "d": 4,
            "nd": 4
        }
    },
    "regions": [
        "chest-front",
        "chest-front"
    ],
    "hands": 1,
    "num_positions": 2,
    "positions": [],
    "motion": {
        "type": "repeated",
        "dir": [
            0,
            0,
            1
        ]
    },
    "palmface": "down",
    "wristTurn": [],
    "morphemes": "",
    "complexity": "",
    "frequency": "",
    "category": ""
}