{
    "sign": "blue",
    "signer": "asl2english",
    "uid": 176,
    "synonyms": [],
    "handshapes": {
        "begin": {
            "d": 19,
            "nd": 19
        },
        "end": {
            "d": 20,
            "nd": 20
        }
    },
    "regions": [
        "R-shoulder",
        "R-shoulder"
    ],
    "hands": 1,
    "num_positions": 2,
    "positions": [],
    "motion": {
        "dir": [
            0,
            0,
            0
        ],
        "type": "repeated"
    },
    "palmface": "horizontal",
    "wristTurn": [],
    "morphemes": "",
    "complexity": "",
    "frequency": "",
    "category": ""
}