{
    "sign": "ns-chicago",
    "signer": "asl2english",
    "uid": 1138,
    "synonyms": [],
    "handshapes": {
        "begin": {
            "d": 30,
            "nd": null
        },
        "end": {
            "d": 30,
            "nd": null
        }
    },
    "regions": [
        0,
        "stomach"
    ],
    "hands": 1,
    "num_positions": 2,
    "positions": [],
    "motion": {
        "dir": [
            1,
            0,
            0
        ],
        "type": "change"
    },
    "palmface": "forward",
    "wristTurn": [],
    "morphemes": "",
    "complexity": "",
    "frequency": "",
    "category": ""
}