{
    "sign": "sorry",
    "signer": "asl2english",
    "uid": 1691,
    "synonyms": [],
    "handshapes": {
        "begin": {
            "d": 82,
            "nd": 82
        },
        "end": {
            "d": 14,
            "nd": 14
        }
    },
    "regions": [
        0,
        0
    ],
    "hands": 1,
    "num_positions": 2,
    "positions": [],
    "motion": {
        "type": "circle",
        "dir": [
            0,
            0,
            0
        ]
    },
    "palmface": "inward",
    "wristTurn": [],
    "morphemes": "",
    "complexity": "",
    "frequency": "",
    "category": ""
}