{
    "sign": "vacuum",
    "signer": "asl2english",
    "uid": 1946,
    "synonyms": [],
    "handshapes": {
        "begin": {
            "d": 14,
            "nd": 14
        },
        "end": {
            "d": 80,
            "nd": 80
        }
    },
    "regions": [
        0,
        0
    ],
    "hands": 1,
    "num_positions": 2,
    "positions": [],
    "motion": {
        "type": "repeated",
        "dir": [
            0,
            0,
            1
        ]
    },
    "palmface": "up",
    "wristTurn": [],
    "morphemes": "",
    "complexity": "",
    "frequency": "",
    "category": ""
}