
{

"@a14596@em2@amphora": { 
	"vb": "49 75 -281 -0",
 },
"@a15634@emo@amphora": { 
	"vb": "51 75 -128 -0",
 },
"@a25477@gli@decoration-vase-2": { 
	"vb": "39 75 -422 -0",
 },
"@a25478@gli@decoration-vase": { 
	"vb": "73 75 -0 -0",
 },
"@a39128@mul@vase": { 
	"vb": "49 75 -330 -0",
 },
"@a40397@nog@amphora-food-drink": { 
	"vb": "51 75 -179 -0",
 },
"@a40399@nog@amphora": { 
	"vb": "55 75 -73 -0",
 },
"@b12144@gameicons-delapouite@amphora": { 
	"vb": "51 75 -230 -0",
 },
"@b13152@gameicons-delapouite@porcelain-vase": { 
	"vb": "43 75 -379 -0",
 },
}
