
{

"@a6174@df-doodle_dings_1_birds_cages@a": { 
	"vb": "75 73 -0 -225",
 },
"@a60407@ian@grus-americana-1": { 
	"vb": "75 53 -375 -67",
 },
"@a60408@ian@grus-americana-2": { 
	"vb": "61 75 -219 -73",
 },
"@a60412@ian@gymnomyza-samoensis": { 
	"vb": "75 55 -280 -132",
 },
"@a60425@ian@haematopus-longirostris": { 
	"vb": "75 51 -355 -181",
 },
"@a60426@ian@haematopus-palliatus": { 
	"vb": "75 61 -355 -120",
 },
"@a60429@ian@haliaeetus-leucocephalus": { 
	"vb": "75 39 -423 -328",
 },
"@a60430@ian@haliaeetus-leucogaster": { 
	"vb": "75 67 -375 -0",
 },
"@a60497@ian@himantopus-himantopus": { 
	"vb": "69 75 -150 -73",
 },
"@a60498@ian@himantopus-mexicanus-eggs": { 
	"vb": "75 55 -144 -375",
 },
"@a60499@ian@himantopus-mexicanus": { 
	"vb": "69 75 -0 -298",
 },
"@a60531@ian@hylocichla-mustelina": { 
	"vb": "51 75 -450 -72",
 },
"@a60539@ian@icterus-galbula-adult": { 
	"vb": "75 47 -333 -232",
 },
"@a60597@ian@irediparra-gallinacea": { 
	"vb": "75 47 -408 -232",
 },
"@a60659@ian@larus-spp": { 
	"vb": "51 75 -146 -150",
 },
"@a60841@ian@melanerpes-erythrocephalus": { 
	"vb": "57 75 -144 -225",
 },
"@a60842@ian@meleagris-gallopavo": { 
	"vb": "69 75 -0 -373",
 },
"@a60891@ian@molothrus-spp": { 
	"vb": "75 73 -150 -0",
 },
"@a61023@ian@nycticorax-nycticorax": { 
	"vb": "75 63 -280 -69",
 },
"@a61050@ian@oporonis-formosus": { 
	"vb": "75 67 -69 -300",
 },
"@a61102@ian@pandion-haliaetus": { 
	"vb": "75 75 -0 -0",
 },
"@a61133@ian@passerculus-sandwichensis": { 
	"vb": "75 75 -0 -75",
 },
"@a61140@ian@pelecanus-occidentalis": { 
	"vb": "59 75 -197 -148",
 },
"@a61141@ian@pelecanus-spp": { 
	"vb": "53 75 -201 -298",
 },
"@a61168@ian@phaethon-aethereus": { 
	"vb": "75 31 -144 -430",
 },
"@a61169@ian@phalacrocorax-auritus": { 
	"vb": "75 75 -75 -0",
 },
"@a61170@ian@phalacrocorax-varius": { 
	"vb": "43 75 -219 -373",
 },
"@a61172@ian@phoenicopterus-minor-flying": { 
	"vb": "75 55 -258 -222",
 },
"@a61173@ian@phoenicopterus-minor-standing": { 
	"vb": "57 75 -144 -300",
 },
"@a61174@ian@phoenicopterus-minor-walking": { 
	"vb": "49 75 -254 -298",
 },
"@a61175@ian@phoenicopterus-ruber-flying": { 
	"vb": "75 55 -303 -279",
 },
"@a61176@ian@phoenicopterus-ruber-wading": { 
	"vb": "45 72 -378 -279",
 },
"@a61177@ian@phoenicopterus-ruber-walking": { 
	"vb": "52 72 -450 -0",
 },
"@a61190@ian@picoides-pubescens": { 
	"vb": "63 75 -430 -147",
 },
"@a61217@ian@platalea-spp": { 
	"vb": "75 75 -0 -150",
 },
"@a61236@ian@pluvialis-fulva": { 
	"vb": "71 75 -75 -150",
 },
"@a61240@ian@poecile-atricapillus": { 
	"vb": "69 75 -75 -225",
 },
"@a61323@ian@protonotaria-citrea": { 
	"vb": "75 67 -69 -367",
 },
"@a61332@ian@ptilinopus-pelewensis": { 
	"vb": "41 75 -262 -373",
 },
"@a61369@ian@recurviostra-americana-winter": { 
	"vb": "75 69 -225 -0",
 },
"@a61370@ian@recurvirostra-americana-summer": { 
	"vb": "75 69 -300 -0",
 },
"@a61371@ian@recurvirostra-novaehollandiae-1": { 
	"vb": "75 43 -405 -412",
 },
"@a61372@ian@recurvirostra-novaehollandiae-2": { 
	"vb": "75 49 -423 -279",
 },
"@a61373@ian@recurvirostra-novaehollandidae-flock": { 
	"vb": "75 35 -256 -187",
 },
"@a61513@ian@rynchops-niger": { 
	"vb": "57 75 -201 -223",
 },
"@a61674@ian@spiza-americana": { 
	"vb": "75 55 -303 -334",
 },
"@a61675@ian@spizella-pusilla": { 
	"vb": "49 75 -356 -389",
 },
"@a61693@ian@sterna-spp": { 
	"vb": "75 75 -75 -75",
 },
"@a61694@ian@sternula-antillarum": { 
	"vb": "75 45 -405 -367",
 },
"@a61722@ian@sturnella-neglecta": { 
	"vb": "53 75 -303 -389",
 },
}
