
{

"@a939@awe@play": { 
	"vb": "71 75 -150 -148",
 },
"@a1327@bat@play": { 
	"vb": "75 75 -0 -0",
 },
"@a1587@bon@children&#39;s-play-area-4250": { 
	"vb": "75 59 -123 -300",
 },
"@a25800@gli@play_cube": { 
	"vb": "75 69 -48 -300",
 },
"@a28061@ico@play": { 
	"vb": "75 75 -0 -75",
 },
"@a29166@jqu@play": { 
	"vb": "71 75 -225 -0",
 },
"@a31719@lug@play": { 
	"vb": "75 59 -211 -298",
 },
"@a31721@lug@play2": { 
	"vb": "75 75 -75 -0",
 },
"@a31723@lug@play3": { 
	"vb": "65 75 -146 -225",
 },
"@a34785@mat@play": { 
	"vb": "61 75 -436 -0",
 },
"@a34855@mat@presentation-play": { 
	"vb": "75 75 -0 -150",
 },
"@a36260@met@play": { 
	"vb": "65 75 -146 -225",
 },
"@a38460@mul@play-area": { 
	"vb": "75 75 -75 -75",
 },
"@a46815@pap@media-playback-start-symbolic": { 
	"vb": "71 75 -75 -225",
 },
"@a46848@pap@multimedia-video-player-symbolic": { 
	"vb": "75 69 -225 -75",
 },
"@a47395@pic@controls-play-back": { 
	"vb": "41 75 -211 -223",
 },
"@a47396@pic@controls-play": { 
	"vb": "41 75 -221 -148",
 },
"@a48286@roc@play": { 
	"vb": "59 75 -262 -144",
 },
"@a48422@sli@control-play": { 
	"vb": "67 75 -321 -142",
 },
"@a48782@solver@2-gonna-play": { 
	"vb": "48 74 -0 -300",
 },
"@a49915@the@control-play": { 
	"vb": "75 75 -150 -0",
 },
"@a52090@typ@media-play-outline": { 
	"vb": "57 75 -388 -142",
 },
"@a52092@typ@media-play-reverse-outline": { 
	"vb": "57 75 -252 -223",
 },
"@a52094@typ@media-play-reverse": { 
	"vb": "57 75 -309 -219",
 },
"@a52096@typ@media-play": { 
	"vb": "57 75 -286 -298",
 },
"@a53429@vaa@play": { 
	"vb": "67 75 -366 -217",
 },
"@a54200@wav@fast-play-forward": { 
	"vb": "75 55 -343 -294",
 },
"@a54201@wav@fast-play-rewind": { 
	"vb": "75 55 -418 -300",
 },
"@a54613@wav@play": { 
	"vb": "65 75 -433 -225",
 },
"@a55587@web@play": { 
	"vb": "69 75 -367 -0",
 },
"@a55588@web@playcircle": { 
	"vb": "75 75 -0 -225",
 },
"@a55590@web@playstore": { 
	"vb": "75 75 -75 -150",
 },
"@a55591@web@playvideo": { 
	"vb": "75 73 -150 -75",
 },
"@a56479@win@control-play-live": { 
	"vb": "43 75 -450 -75",
 },
"@a56480@win@control-play": { 
	"vb": "51 75 -445 -150",
 },
"@a56882@win@monitor-play": { 
	"vb": "75 67 -300 -75",
 },
"@b13681@gameicons-guard13007@play-button": { 
	"vb": "75 67 -375 -75",
 },
"@b15140@gameicons-quoting@card-play": { 
	"vb": "71 75 -296 -0",
 },
}
