
{

"@a731@awe@desktop": { 
	"vb": "75 67 -525 -75",
 },
"@a14408@ele@desktop": { 
	"vb": "75 69 -0 -75",
 },
"@a14832@em2@desktop-computer": { 
	"vb": "75 75 -0 -0",
 },
"@a15914@emo@desktop": { 
	"vb": "75 75 -75 -0",
 },
"@a17582@fir@u1f4bb-personalcomputer": { 
	"vb": "75 71 -742 -0",
 },
"@a27344@icf@desktop": { 
	"vb": "75 67 -375 -75",
 },
"@a28672@jqe@personal-computer": { 
	"vb": "75 75 -150 -0",
 },
"@a29030@jqu@desktop": { 
	"vb": "75 67 -450 -75",
 },
"@a29340@knl@1-computer-1": { 
	"vb": "75 75 -225 -0",
 },
"@a29589@knl@computer-2": { 
	"vb": "67 75 -675 -0",
 },
"@a29671@knl@monitor": { 
	"vb": "75 63 -600 -75",
 },
"@a30150@lib@desktop": { 
	"vb": "75 69 -75 -75",
 },
"@a30151@lib@device-desktop": { 
	"vb": "75 75 -300 -0",
 },
"@a33263@mat@desktop-mac": { 
	"vb": "75 71 -750 -71",
 },
"@a46930@pap@preferences-desktop-remote-desktop-symbolic": { 
	"vb": "75 75 -375 -0",
 },
"@a46931@pap@preferences-desktop-screensaver-symbolic": { 
	"vb": "75 75 -450 -0",
 },
"@a46933@pap@preferences-desktop-wallpaper-symbolic": { 
	"vb": "75 75 -525 -0",
 },
"@a48518@sli@screen-desktop": { 
	"vb": "75 63 -675 -75",
 },
"@a48588@small@device-computer": { 
	"vb": "75 69 -150 -75",
 },
"@a49927@the@desktop": { 
	"vb": "75 69 -225 -75",
 },
"@a51922@typ@device-desktop": { 
	"vb": "75 69 -300 -75",
 },
"@a53172@vaa@desktop": { 
	"vb": "75 75 -600 -0",
 },
"@a54121@wav@desktop-mac": { 
	"vb": "75 71 -817 -0",
 },
"@a54122@wav@desktop-windows": { 
	"vb": "75 71 -825 -71",
 },
"@a54123@wav@desktop": { 
	"vb": "75 59 -900 -71",
 },
"@a57620@xei@desktop-monitor": { 
	"vb": "75 71 -892 -0",
 },
}
